omnivista_py/__init__.py
omnivista_py/exceptions.py
omnivista_py/omnivista.py
omnivista_py_phillipyosief-0.3.6.dist-info/LICENSE
omnivista_py_phillipyosief-0.3.6.dist-info/METADATA
omnivista_py_phillipyosief-0.3.6.dist-info/WHEEL
omnivista_py_phillipyosief-0.3.6.dist-info/top_level.txt
omnivista_py_phillipyosief-0.3.6.dist-info/RECORD
